<?xml version="1.0" encoding="UTF-8"?>
<!DOCTYPE locale SYSTEM "../../../../../lib/pkp/dtd/locale.dtd">

<!--
  * plugins/themes/defaultManuscript/locale/en_US/locale.xml
  *
  * Copyright (c) 2014-2017 Simon Fraser University Library
  * Copyright (c) 2003-2017 John Willinsky
  * Distributed under the GNU GPL v2. For full terms see the file docs/COPYING.
  *
  * Localization strings
  -->

<locale name="en_US" full_name="U.S. English">
	<message key="plugins.themes.ubma.name">UBMA</message>
	<message key="plugins.themes.ubma.description">A theme adapted to the needs of Mannheim UL.</message>
	<message key="plugins.themes.ubma.option.typography.montserrat_notoSerif">Montserrat/Noto Serif</message>
	<message key="plugins.themes.ubma.option.accentColour.label">Accent Colour</message>
    <message key="submissions.downloads">Downloads</message>

<!-- Hier folgen alle Übersetzungen für Anpassungen auf der Homepage -->
    <message key="site.aboutThis"><![CDATA[]]></message>
    <message key="site.furtherInfo"></message>
    <message key="site.ourService">Our service</message>
    <message key="site.aboutOJS">About OJS</message>
    <message key="site.contact">Contact</message>
    <message key="site.ourJournals">Diese Zeitschriften finden Sie bereits auf unserer OJS-Plattform:</message>

    <message key="site.journalAllIssues">All Issues</message>
</locale>
